capture0/__init__.py
capture0/config.py
capture0/decode.py
capture0/main.py
capture0/storage.py
capture0/forms/__init__.py
capture0/forms/countries.py
capture0/forms/home_form.py
capture0/static/__init__.py
capture0/static/css/bootstrap-theme.css
capture0/static/css/bootstrap-theme.css.map
capture0/static/css/bootstrap-theme.min.css
capture0/static/css/bootstrap-theme.min.css.map
capture0/static/css/bootstrap.css
capture0/static/css/bootstrap.css.map
capture0/static/css/bootstrap.min.css
capture0/static/css/bootstrap.min.css.map
capture0/static/css/site.css
capture0/static/fonts/glyphicons-halflings-regular.eot
capture0/static/fonts/glyphicons-halflings-regular.svg
capture0/static/fonts/glyphicons-halflings-regular.ttf
capture0/static/fonts/glyphicons-halflings-regular.woff
capture0/static/fonts/glyphicons-halflings-regular.woff2
capture0/static/images/0.png
capture0/static/images/0_100px.png
capture0/static/images/0_fade.png
capture0/static/js/bootstrap.js
capture0/static/js/bootstrap.min.js
capture0/static/js/npm.js
capture0/templates/__init__.py
capture0/templates/done.html.j2
capture0/templates/index.html.j2
capture0/templates/layout.html.j2
capture0-0.1.45.dist-info/DESCRIPTION.rst
capture0-0.1.45.dist-info/METADATA
capture0-0.1.45.dist-info/RECORD
capture0-0.1.45.dist-info/WHEEL
capture0-0.1.45.dist-info/entry_points.txt
capture0-0.1.45.dist-info/metadata.json
capture0-0.1.45.dist-info/top_level.txt
capture0_data/__init__.py
capture0_data/company_info.py
capture0_data/online_handles.py
capture0_data/online_messages.py
capture0_data/utils.py
capture0_static/__init__.py
tmp/__init__.py
tmp/decode_countries.py
