Metadata-Version: 2.0
Name: capture0
Version: 0.1.45
Summary: A tool for capturing data from the web.
Home-page: https://github.com/salimfadhley/capture0
Author: Salim Fadhley
Author-email: salimfadhley@gmail.com
License: MIT
Platform: UNKNOWN
Requires-Dist: click
Requires-Dist: flask
Requires-Dist: cachetools
Requires-Dist: Flask-WTF
Requires-Dist: markdown
Requires-Dist: six
Requires-Dist: pytz
